verbit/streaming_client.py
verbit_streaming_sdk-1.0.0.dist-info/METADATA
verbit_streaming_sdk-1.0.0.dist-info/WHEEL
verbit_streaming_sdk-1.0.0.dist-info/top_level.txt
verbit_streaming_sdk-1.0.0.dist-info/RECORD
