Metadata-Version: 2.1
Name: verbit-streaming-sdk
Version: 1.0.0
Summary: Client SDK for Verbit's Streaming Speech Recognition services
Home-page: https://github.com/verbit-ai/verbit-streaming-python-sdk
License: UNKNOWN
Platform: UNKNOWN
Requires-Python: >=3.8
Requires-Dist: websocket-client (<2,>1)
Requires-Dist: tenacity (<9,>8)
Requires-Dist: requests (<3)
